uc_daemon/__init__.py
uc_daemon-0.0.1.dist-info/LICENSE
uc_daemon-0.0.1.dist-info/METADATA
uc_daemon-0.0.1.dist-info/WHEEL
uc_daemon-0.0.1.dist-info/top_level.txt
uc_daemon-0.0.1.dist-info/RECORD
