Metadata-Version: 2.1
Name: uc-daemon
Version: 0.0.1
Summary: A set of classes and functions for demonizing a process and related tools..
Home-page: https://github.com/dentist128/uc_daemon
Author: Eduard S. Markelov
Author-email: markeloveduard@gmail.com
License: UNKNOWN
Platform: UNKNOWN
Classifier: Programming Language :: Python :: 3
Classifier: License :: OSI Approved :: GNU Affero General Public License v3
Classifier: Operating System :: OS Independent
Requires-Python: >=2.6, <4
